setup.py
Helloworldnishantsalot.egg-info/PKG-INFO
Helloworldnishantsalot.egg-info/SOURCES.txt
Helloworldnishantsalot.egg-info/dependency_links.txt
Helloworldnishantsalot.egg-info/not-zip-safe
Helloworldnishantsalot.egg-info/top_level.txt
scipytest/ScipyTest.py
scipytest/__init__.py
testbuiltins/__init__.py
testbuiltins/testbuiltinFunctions.py
testnumpy/__init__.py
testnumpy/testnp.py
testpython/Plot.py
testpython/RandomWalk.py
testpython/__init__.py
testpython/app.py
testpython/inheritance.py
testpython/visual.py
threadingtest/Hi.py
threadingtest/PriorityQueueTest.py
threadingtest/__init__.py