Metadata-Version: 1.0
Name: Helloworldnishantsalot
Version: 0.2
Summary: Add static script_dir() method to Path
Home-page: UNKNOWN
Author: nishantsalot
Author-email: nishantsalot@gmail.com
License: MIT
Platform: UNKNOWN
